mollie_cli/__about__.py
mollie_cli/__init__.py
mollie_cli/client.py
mollie_cli/commandline.py
mollie_cli/formatting.py
mollie_cli-0.1.1.dist-info/METADATA
mollie_cli-0.1.1.dist-info/WHEEL
mollie_cli-0.1.1.dist-info/entry_points.txt
mollie_cli-0.1.1.dist-info/licenses/LICENSE.txt
mollie_cli-0.1.1.dist-info/RECORD
