Metadata-Version: 2.1
Name: mollie-cli
Version: 0.1.1
Summary: Simple commandline client for Mollie
Project-URL: Documentation, https://github.com/whyscream/mollie-cli#readme
Project-URL: Issues, https://github.com/whyscream/mollie-cli/issues
Project-URL: Source, https://github.com/whyscream/mollie-cli
Author-email: Tom Hendrikx <tom@whyscream.net>
License-File: LICENSE.txt
Keywords: cli,mollie,payments
Classifier: Development Status :: 4 - Beta
Classifier: Programming Language :: Python
Classifier: Programming Language :: Python :: 3.7
Classifier: Programming Language :: Python :: 3.8
Classifier: Programming Language :: Python :: 3.9
Classifier: Programming Language :: Python :: 3.10
Classifier: Programming Language :: Python :: 3.11
Classifier: Programming Language :: Python :: Implementation :: CPython
Classifier: Programming Language :: Python :: Implementation :: PyPy
Requires-Python: >=3.7
Requires-Dist: click<9,>=8.1.3
Requires-Dist: mollie-api-python<4,>=3.0.0rc1
Requires-Dist: tabulate>=0.9.0
